CHANGELOG.txt
LICENSE.txt
MANIFEST.in
README.rst
cxfreeze_setup.py
requirements.txt
setup.py
automator/Automator.py
automator/Gautoauto.py
automator/LICENSE.txt
automator/MplCanvas.py
automator/Ui_Automator.py
automator/Ui_Automator.ui
automator/Ui_DialogFileLoc.py
automator/Ui_DialogFileLoc.ui
automator/Ui_DialogOrientGainRef.py
automator/Ui_DialogOrientGainRef.ui
automator/Ui_ViewDialog.py
automator/Ui_ViewDialog.ui
automator/Ui_ViewWidget.py
automator/Ui_ViewWidget.ui
automator/ViewWidget.py
automator/__config__.py
automator/__init__.py
automator/__main__.py
automator/__version__.py
automator/compileUI.py
automator/setup.py
automator/zorroSkulkManager.py
automator/icons/CINAlogo.png
automator/icons/application-resize.png
automator/icons/arrow-180.png
automator/icons/arrow.png
automator/icons/boxes.png
automator/icons/color.png
automator/icons/colorbar.png
automator/icons/control-pause.png
automator/icons/control.png
automator/icons/folder.png
automator/icons/go-next.png
automator/icons/histogram.png
automator/icons/logscale.png
automator/icons/magnifier-zoom-in.png
automator/icons/magnifier-zoom-out.png
automator/icons/monitor-dead.png
automator/icons/monitor-live.png
automator/icons/process-stop.png
automator/icons/question.png
automator/icons/user-trash.png
automator/icons/view-refresh.png
numexprz/__config__.py
numexprz/__init__.py
numexprz/cpuinfo.py
numexprz/expressions.py
numexprz/interpreter.cp36-win_amd64.pyd
numexprz/necompiler.py
numexprz/setup.py
numexprz/utils.py
numexprz/version.py
zorro/__config__.py
zorro/__init__.py
zorro/__main__.py
zorro/__version__.py
zorro/extract.py
zorro/setup.py
zorro/zorro.py
zorro/zorro_plotting.py
zorro/zorro_util.py
zorro/scripts/2dxZorro.py
zorro/scripts/__init__.py
zorro/scripts/analyticPhantom.py
zorro/scripts/box2star.py
zorro/scripts/boxFixer.py
zorro/scripts/calcMeanFRCs.py
zorro/scripts/gctfHisto.py
zorro/scripts/gctfLogParser.py
zorroautomator-0.7.4b0.dist-info/DESCRIPTION.rst
zorroautomator-0.7.4b0.dist-info/METADATA
zorroautomator-0.7.4b0.dist-info/RECORD
zorroautomator-0.7.4b0.dist-info/WHEEL
zorroautomator-0.7.4b0.dist-info/entry_points.txt
zorroautomator-0.7.4b0.dist-info/metadata.json
zorroautomator-0.7.4b0.dist-info/top_level.txt
