Metadata-Version: 2.0
Name: zorroautomator
Version: 0.7.4b0
Summary: Zorro Automator - dose-fractionated image registrator
Home-page: https://github.com/C-CINA/Zorro
Author: Robert A. McLeod
Author-email: robert.mcleod@unibas.ch
License: BSD
Requires-Dist: matplotlib (>=1.4)
Requires-Dist: mrcz
Requires-Dist: numpy (>=1.8)
Requires-Dist: pyfftw (>=0.10.4)
Requires-Dist: scipy (>=0.12.0)
Requires-Dist: pyside; python_version <= "3.4"
